django_logging/__init__.py
django_logging/apps.py
django_logging/constants/__init__.py
django_logging/constants/ansi_colors.py
django_logging/constants/config_types.py
django_logging/constants/date_format_directives.py
django_logging/constants/default_settings.py
django_logging/constants/log_format_options.py
django_logging/constants/log_format_specifiers.py
django_logging/constants/required_email_settings.py
django_logging/contextvar/__init__.py
django_logging/contextvar/contextvar_manager.py
django_logging/decorators/__init__.py
django_logging/decorators/execution_tracking.py
django_logging/filters/__init__.py
django_logging/filters/context_filter.py
django_logging/filters/log_level_filter.py
django_logging/formatters/__init__.py
django_logging/formatters/base.py
django_logging/formatters/colored_formatter.py
django_logging/formatters/flat_formatter.py
django_logging/formatters/json_formatter.py
django_logging/formatters/xml_formatter.py
django_logging/handlers/__init__.py
django_logging/handlers/email_handler.py
django_logging/management/__init__.py
django_logging/management/commands/__init__.py
django_logging/management/commands/generate_pretty_json.py
django_logging/management/commands/generate_pretty_xml.py
django_logging/management/commands/logs_size_audit.py
django_logging/management/commands/send_logs.py
django_logging/middleware/__init__.py
django_logging/middleware/base.py
django_logging/middleware/monitor_log_size.py
django_logging/middleware/request_middleware.py
django_logging/settings/__init__.py
django_logging/settings/checks.py
django_logging/settings/conf.py
django_logging/settings/manager.py
django_logging/static/LogiBoard/css/app.css
django_logging/static/LogiBoard/css/error_response.css
django_logging/static/LogiBoard/imgs/Lazarus.jpeg
django_logging/static/LogiBoard/imgs/close-50.png
django_logging/static/LogiBoard/imgs/done-50.png
django_logging/static/LogiBoard/imgs/exclamation-mark.png
django_logging/static/LogiBoard/imgs/file-icon.png
dj_logging-2.0.1.dist-info/AUTHORS.md
dj_logging-2.0.1.dist-info/LICENCE
dj_logging-2.0.1.dist-info/METADATA
dj_logging-2.0.1.dist-info/WHEEL
dj_logging-2.0.1.dist-info/RECORD
