Metadata-Version: 2.1
Name: dj-logging
Version: 2.0.1
Summary: A package for logging in django applications
License: MIT
Keywords: django_logging,django,logging
Author: ARYAN-NIKNEZHAD
Author-email: aryan513966@gmail.com
Requires-Python: >=3.9,<4.0
Classifier: Development Status :: 3 - Alpha
Classifier: Environment :: Web Environment
Classifier: Framework :: Django
Classifier: Framework :: Django :: 4.2
Classifier: Framework :: Django :: 5.0
Classifier: Framework :: Django :: 5.1
Classifier: Intended Audience :: Developers
Classifier: License :: OSI Approved :: MIT License
Classifier: Operating System :: OS Independent
Classifier: Programming Language :: Python
Classifier: Programming Language :: Python :: 3
Classifier: Programming Language :: Python :: 3.9
Classifier: Programming Language :: Python :: 3.10
Classifier: Programming Language :: Python :: 3.11
Classifier: Programming Language :: Python :: 3.12
Classifier: Programming Language :: Python :: 3.13
Classifier: Programming Language :: Python :: 3 :: Only
Classifier: Topic :: Software Development :: Libraries :: Python Modules
Requires-Dist: django (>=4.2,<5.0) ; python_version >= "3.9" and python_version < "3.10"
Requires-Dist: django (>=4.2,<5.3) ; python_version >= "3.10"
Project-URL: Changelog, https://github.com/lazarus-org/django_logging/blob/main/CHANGELOG.md
Project-URL: Documentation, https://django-logging.readthedocs.io
Project-URL: Issues, https://github.com/lazarus-org/django_logging/issues
Project-URL: Source Code, https://github.com/lazarus-org/django_logging
